[
  {
    "ContainingType": "dogwebMVC.Controllers.AuthApiController",
    "Method": "CheckLogin",
    "RelativePath": "api/AuthApi/check",
    "HttpMethod": "GET",
    "IsController": true,
    "Order": 0,
    "Parameters": [],
    "ReturnTypes": []
  },
  {
    "ContainingType": "dogwebMVC.Controllers.AuthApiController",
    "Method": "GetUser",
    "RelativePath": "api/AuthApi/getUser",
    "HttpMethod": "GET",
    "IsController": true,
    "Order": 0,
    "Parameters": [],
    "ReturnTypes": []
  },
  {
    "ContainingType": "dogwebMVC.Controllers.AuthApiController",
    "Method": "Login",
    "RelativePath": "api/AuthApi/login",
    "HttpMethod": "POST",
    "IsController": true,
    "Order": 0,
    "Parameters": [],
    "ReturnTypes": []
  },
  {
    "ContainingType": "dogwebMVC.Controllers.AuthApiController",
    "Method": "Logout",
    "RelativePath": "api/AuthApi/logout",
    "HttpMethod": "POST",
    "IsController": true,
    "Order": 0,
    "Parameters": [],
    "ReturnTypes": []
  },
  {
    "ContainingType": "dogwebMVC.Controllers.AuthApiController",
    "Method": "Register",
    "RelativePath": "api/AuthApi/register",
    "HttpMethod": "POST",
    "IsController": true,
    "Order": 0,
    "Parameters": [],
    "ReturnTypes": []
  }
]